CHANGES
MANIFEST.in
README.txt
setup.py
pyramid_perfstat/__init__.py
pyramid_perfstat/perf_serializer.py
pyramid_perfstat/utils.py
pyramid_perfstat/views.py
pyramid_perfstat.egg-info/PKG-INFO
pyramid_perfstat.egg-info/SOURCES.txt
pyramid_perfstat.egg-info/dependency_links.txt
pyramid_perfstat.egg-info/not-zip-safe
pyramid_perfstat.egg-info/requires.txt
pyramid_perfstat.egg-info/top_level.txt
pyramid_perfstat/static/images/asc.gif
pyramid_perfstat/static/images/bg.gif
pyramid_perfstat/static/images/desc.gif
pyramid_perfstat/static/js/jquery-1.6.4.min.js
pyramid_perfstat/templates/reporting.mako